{
    "bookings": {
        "data": {
            "cols": [{
                    "id": "",
                    "label": "Biljett",
                    "pattern": "",
                    "type": "string"
                },
                {
                    "id": "",
                    "label": "Antal bokningar",
                    "pattern": "",
                    "type": "number"
                }
            ],
            "rows": [{
                    "c": [{
                        "v": "Premium",
                        "f": null
                    }, {
                        "v": 3,
                        "f": "premium"
                    }]
                },
                {
                    "c": [{
                        "v": "Business",
                        "f": null
                    }, {
                        "v": 1,
                        "f": "business"
                    }]
                },
                {
                    "c": [{
                        "v": "Basic",
                        "f": null
                    }, {
                        "v": 1,
                        "f": "basic"
                    }]
                },
                {
                    "c": [{
                        "v": "Economy",
                        "f": null
                    }, {
                        "v": 1,
                        "f": "economy"
                    }]
                },
                {
                    "c": [{
                        "v": "Simple",
                        "f": null
                    }, {
                        "v": 2,
                        "f": "simple"
                    }]
                }
            ]
        },
        "options": {
            "regular": {
                "title": "Antal bokningar",
                "colors": ["#ee7365", "#444f63"],
                "chartArea": {
                    "left": "15%",
                    "top": "13%",
                    "height": "80%",
                    "width": "60%"
                },
                "animation": {
                    "startup": true,
                    "duration": 300,
                    "easing": "out"
                }
            },
            "pie": {
                "title": "Antal bokningar",
                "colors": ["#ee7365", "#444f63"],
                "chartArea": {
                    "left": "25%",
                    "top": "13%",
                    "height": "80%",
                    "width": "100%"
                },
                "animation": {
                    "startup": true,
                    "duration": 300,
                    "easing": "out"
                },
                "pieHole": "0.4"
            }
        }
    },
    "nationalities": {
        "data": {
            "cols": [{
                    "id": "",
                    "label": "Land",
                    "pattern": "",
                    "type": "string"
                },
                {
                    "id": "",
                    "label": "Antal",
                    "pattern": "",
                    "type": "number"
                }
            ],
            "rows": [{
                    "c": [{
                        "v": "Sverige",
                        "f": null
                    }, {
                        "v": 300,
                        "f": null
                    }]
                },
                {
                    "c": [{
                        "v": "Tyskland",
                        "f": null
                    }, {
                        "v": 100,
                        "f": null
                    }]
                },
                {
                    "c": [{
                        "v": "USA",
                        "f": null
                    }, {
                        "v": 100,
                        "f": null
                    }]
                },
                {
                    "c": [{
                        "v": "Brasilien",
                        "f": null
                    }, {
                        "v": 200,
                        "f": null
                    }]
                },
                {
                    "c": [{
                        "v": "Kanada",
                        "f": null
                    }, {
                        "v": 250,
                        "f": null
                    }]
                }
            ]
        },
        "options": {
            "regular": {
                "title": "Nationaliteter",
                "colors": ["#ee7365", "#444f63"],
                "chartArea": {
                    "left": "5%",
                    "top": "13%",
                    "height": "80%",
                    "width": "70%"
                },
                "animation": {
                    "startup": true,
                    "duration": 300,
                    "easing": "out"
                }
            },
            "pie": {
                "title": "Nationaliteter",
                "colors": ["#ee7365", "#444f63"],
                "chartArea": {
                    "left": "25%",
                    "top": "13%",
                    "height": "80%",
                    "width": "100%"
                },
                "animation": {
                    "startup": true,
                    "duration": 300,
                    "easing": "out"
                },
                "pieHole": "0.4"
            }
        }
    },
    "sale": {
        "data": {
            "cols": [{
                    "id": "",
                    "label": "År",
                    "pattern": "",
                    "type": "string"
                },
                {
                    "id": "",
                    "label": "Utgifter",
                    "pattern": "",
                    "type": "number"
                },
                {
                    "id": "",
                    "label": "Vinst",
                    "pattern": "",
                    "type": "number"
                }
            ],
            "rows": [{
                    "c": [{
                        "v": "2014",
                        "f": null
                    }, {
                        "v": 800,
                        "f": null
                    }, {
                        "v": 747,
                        "f": null
                    }]
                },
                {
                    "c": [{
                        "v": "2015",
                        "f": null
                    }, {
                        "v": 489,
                        "f": null
                    }, {
                        "v": 585,
                        "f": null
                    }]
                },
                {
                    "c": [{
                        "v": "2016",
                        "f": null
                    }, {
                        "v": 1020,
                        "f": null
                    }, {
                        "v": 302,
                        "f": null
                    }]
                },
                {
                    "c": [{
                        "v": "2017",
                        "f": null
                    }, {
                        "v": 525,
                        "f": null
                    }, {
                        "v": 391,
                        "f": null
                    }]
                }
            ]
        },
        "options": {
            "regular": {
                "title": "Omsättning",
                "colors": ["#ee7365", "#444f63"],
                "chartArea": {
                    "left": "5%",
                    "top": "13%",
                    "height": "80%",
                    "width": "70%"
                },
                "animation": {
                    "startup": true,
                    "duration": 300,
                    "easing": "out"
                }
            },
            "pie": {
                "title": "Omsättning",
                "colors": ["#ee7365", "#444f63"],
                "chartArea": {
                    "left": "25%",
                    "top": "13%",
                    "height": "80%",
                    "width": "100%"
                },
                "animation": {
                    "startup": true,
                    "duration": 300,
                    "easing": "out"
                },
                "pieHole": "0.4"
            }
        }
    },
    "todaysEvent": {
        "data": {
            "cols": [{
                    "id": "",
                    "label": "Land",
                    "pattern": "",
                    "type": "string"
                },
                {
                    "id": "",
                    "label": "Män",
                    "pattern": "",
                    "type": "number"
                },
                {
                    "id": "",
                    "label": "Kvinnor",
                    "pattern": "",
                    "type": "number"
                }
            ],
            "rows": [{
                    "c": [{
                        "v": "Sverige",
                        "f": null
                    }, {
                        "v": 300,
                        "f": null
                    }, {
                        "v": 700,
                        "f": null
                    }]
                },
                {
                    "c": [{
                        "v": "Norge",
                        "f": null
                    }, {
                        "v": 550,
                        "f": null
                    }, {
                        "v": 200,
                        "f": null
                    }]
                },
                {
                    "c": [{
                        "v": "Danmark",
                        "f": null
                    }, {
                        "v": 57,
                        "f": null
                    }, {
                        "v": 1000,
                        "f": null
                    }]
                },
                {
                    "c": [{
                        "v": "Tyskland",
                        "f": null
                    }, {
                        "v": 600,
                        "f": null
                    }, {
                        "v": 600,
                        "f": null
                    }]
                },
                {
                    "c": [{
                        "v": "USA",
                        "f": null
                    }, {
                        "v": 2000,
                        "f": null
                    }, {
                        "v": 1,
                        "f": null
                    }]
                },
                {
                    "c": [{
                        "v": "Finland",
                        "f": null
                    }, {
                        "v": 157,
                        "f": null
                    }, {
                        "v": 339,
                        "f": null
                    }]
                },
                {
                    "c": [{
                        "v": "Schweiz",
                        "f": null
                    }, {
                        "v": 150,
                        "f": null
                    }, {
                        "v": 491,
                        "f": null
                    }]
                },
                {
                    "c": [{
                        "v": "Spanien",
                        "f": null
                    }, {
                        "v": 296,
                        "f": null
                    }, {
                        "v": 239,
                        "f": null
                    }]
                }
            ]
        },
        "options": {
            "regular": {
                "title": "Dagens event",
                "colors": ["#ee7365", "#444f63"],
                "chartArea": {
                    "left": "5%",
                    "top": "13%",
                    "height": "80%",
                    "width": "70%"
                },
                "animation": {
                    "startup": true,
                    "duration": 300,
                    "easing": "out"
                }
            },
            "pie": {
                "title": "Dagens event",
                "colors": ["#ee7365", "#444f63"],
                "chartArea": {
                    "left": "25%",
                    "top": "13%",
                    "height": "80%",
                    "width": "100%"
                },
                "animation": {
                    "startup": true,
                    "duration": 300,
                    "easing": "out"
                },
                "pieHole": "0.4"
            }
        }
    }
}